{
  "forge_marker": 1,
  "defaults": {
    "textures": {
      "all": "terrafirmacraft:blocks/plants/Blueberry",
      "particle": "terrafirmacraft:blocks/plants/Blueberry"
    },
    "custom": {
      "minx": "1.6",
      "minz": "1.6",
      "maxx": "12.8",
      "maxz": "12.8",
      "maxy": "13.6"
    },
    "model": "terrafirmacraft:minecraft_cube_all",
    "transform": "forge:default-block"
  },
  "variants": {
    "berry": {
      "true": {
        "textures": {
          "all": "terrafirmacraft:blocks/plants/Blueberry Berry"
        }
      },
      "false": {}
    },
    "east": {
      "custom": {
        "maxx": "16"
      }
    },
    "west": {
      "custom": {
        "minx": "0"
      }
    },
    "north": {
      "custom": {
        "minz": "0"
      }
    },
    "south": {
      "custom": {
        "maxz": "16"
      }
    },
    "up": {
      "custom": {
        "maxy": "16"
      }
    }
  }
}